{
    "mappings": {
      "issues": {
        "properties": {
          "author_association": {
            "type": "text",
            "fields": {
              "keyword": {
                "type": "keyword",
                "ignore_above": 256
              }
            }
          },
          "body": {
            "type": "text",
            "fields": {
              "keyword": {
                "type": "keyword",
                "ignore_above": 256
              }
            }
          },
          "closed_at": {
            "type": "date"
          },
          "comments": {
            "type": "long"
          },
          "created_at": {
            "type": "date"
          },
          "id": {
            "type": "long"
          },
          "number": {
            "type": "long"
          },
          "state": {
            "type": "text",
            "fields": {
              "keyword": {
                "type": "keyword",
                "ignore_above": 256
              }
            }
          },
          "title": {
            "type": "text",
            "fields": {
              "keyword": {
                "type": "keyword",
                "ignore_above": 256
              }
            }
          },
          "updated_at": {
            "type": "date"
          },
          "url": {
            "type": "text",
            "fields": {
              "keyword": {
                "type": "keyword",
                "ignore_above": 256
              }
            }
          }
        }
      }
    },
    "settings": {
      "index": {
        "number_of_shards": "5",
        "number_of_replicas": "1"
      }
    }
}
